LICENSE
MANIFEST.in
README.rst
requirements.txt
setup.py
bin/ofxfake.py
bin/ofxfix.py
fixofx/__init__.py
fixofx.egg-info/PKG-INFO
fixofx.egg-info/SOURCES.txt
fixofx.egg-info/dependency_links.txt
fixofx.egg-info/requires.txt
fixofx.egg-info/top_level.txt
fixofx/ofx/__init__.py
fixofx/ofx/account.py
fixofx/ofx/builder.py
fixofx/ofx/client.py
fixofx/ofx/document.py
fixofx/ofx/error.py
fixofx/ofx/filetyper.py
fixofx/ofx/generator.py
fixofx/ofx/institution.py
fixofx/ofx/parser.py
fixofx/ofx/request.py
fixofx/ofx/response.py
fixofx/ofx/validators.py
fixofx/ofxtools/__init__.py
fixofx/ofxtools/ofc_converter.py
fixofx/ofxtools/ofc_parser.py
fixofx/ofxtools/ofx_statement.py
fixofx/ofxtools/qif_converter.py
fixofx/ofxtools/qif_parser.py
fixofx/ofxtools/util.py