Metadata-Version: 1.1
Name: fixofx
Version: 3.0
Summary: Canonicalize various financial data file formats to OFX 2 (a.k.a XML)
Home-page: http://github.com/henriquebastos/fixofx
Author: Henrique Bastos
Author-email: henrique@bastos.net
License: Apache 2.0
Keywords: ofx,ofc,qif,converter,xml
Platform: UNKNOWN
Classifier: Development Status :: 5 - Production/Stable
Classifier: Intended Audience :: Developers
Classifier: Intended Audience :: Financial and Insurance Industry
Classifier: License :: OSI Approved :: Apache Software License
Classifier: Natural Language :: English
Classifier: Operating System :: OS Independent
Classifier: Programming Language :: Python :: 3
Classifier: Topic :: Software Development :: Libraries
Classifier: Topic :: Text Processing
